remotescript/__init__.py
remotescript/__main__.py
remotescript/_core.py
remotescript/_imports.py
remotescript/_utils.py
remotescript/py.typed
remotescript-0.0.3.dist-info/LICENSE
remotescript-0.0.3.dist-info/METADATA
remotescript-0.0.3.dist-info/WHEEL
remotescript-0.0.3.dist-info/top_level.txt
remotescript-0.0.3.dist-info/RECORD
