Metadata-Version: 2.1
Name: remotescript
Version: 0.0.3
Author: Ben Guevel, Caleb Pham, Edward Gibson, Caden Ford, Andrew Depke
Author-email: Justin Davis <davisjustin302@gmail.com>
Maintainer-email: Justin Davis <davisjustin302@gmail.com>
Project-URL: Homepage, https://github.com/justincdavis/remotescript
Project-URL: Bug Tracker, https://github.com/justincdavis/remotescript/issues
Classifier: Development Status :: 4 - Beta
Classifier: Programming Language :: Python :: 3 :: Only
Classifier: Programming Language :: Python :: 3
Classifier: Programming Language :: Python :: 3.8
Classifier: Programming Language :: Python :: 3.9
Classifier: Programming Language :: Python :: 3.10
Classifier: Programming Language :: Python :: 3.11
Classifier: Programming Language :: Python :: 3.12
Classifier: Programming Language :: Python :: Implementation :: CPython
Classifier: License :: OSI Approved :: MIT License
Classifier: Operating System :: POSIX :: Linux
Classifier: Natural Language :: English
Classifier: Topic :: System :: Hardware
Classifier: Topic :: Software Development
Classifier: Intended Audience :: Developers
Classifier: Intended Audience :: Science/Research
Classifier: Intended Audience :: Education
Classifier: Typing :: Typed
Requires-Python: <=3.13,>=3.8
License-File: LICENSE
Requires-Dist: paramiko >=3.4.0
Requires-Dist: scp >=0.15.0
Requires-Dist: stdlib-list >=0.10.0
Provides-Extra: ci
Requires-Dist: ruff >=0.2.2 ; extra == 'ci'
Requires-Dist: mypy >=1.8.0 ; extra == 'ci'
Requires-Dist: types-setuptools >=57.0.0 ; extra == 'ci'
Requires-Dist: types-paramiko >=3.4.0 ; extra == 'ci'
Provides-Extra: dev
Requires-Dist: remotescript[ci] ; extra == 'dev'
Requires-Dist: remotescript[test] ; extra == 'dev'
Requires-Dist: remotescript[docs] ; extra == 'dev'
Requires-Dist: twine >=4.0.0 ; extra == 'dev'
Requires-Dist: wheel >=0.37.0 ; extra == 'dev'
Requires-Dist: bumpver >=2023.1126 ; extra == 'dev'
Requires-Dist: pyclean >=2.7.0 ; extra == 'dev'
Requires-Dist: pyright >=1.1.348 ; extra == 'dev'
Provides-Extra: docs
Requires-Dist: sphinx >=6.1.0 ; extra == 'docs'
Requires-Dist: sphinx-rtd-theme >=1.3.0 ; extra == 'docs'
Requires-Dist: myst-parser >=1.0.0 ; extra == 'docs'
Provides-Extra: test
Requires-Dist: pytest >=6.2.0 ; extra == 'test'
